bcm_pricing_calculator_mcp_server/__init__.py
bcm_pricing_calculator_mcp_server/client.py
bcm_pricing_calculator_mcp_server/consts.py
bcm_pricing_calculator_mcp_server/pricing_discovery.py
bcm_pricing_calculator_mcp_server/server.py
bcm_pricing_calculator_mcp_server-1.0.0.dist-info/METADATA
bcm_pricing_calculator_mcp_server-1.0.0.dist-info/WHEEL
bcm_pricing_calculator_mcp_server-1.0.0.dist-info/entry_points.txt
bcm_pricing_calculator_mcp_server-1.0.0.dist-info/licenses/LICENSE
bcm_pricing_calculator_mcp_server-1.0.0.dist-info/RECORD
