Metadata-Version: 2.4
Name: bcm-pricing-calculator-mcp-server
Version: 1.0.0
Summary: Model Context Protocol (MCP) server for AWS Billing and Cost Management Pricing Calculator
Project-URL: Documentation, https://docs.aws.amazon.com/cli/latest/reference/bcm-pricing-calculator/
Project-URL: Source, https://github.com/oreokebu-dev/bcm-pricing-calculator-mcp-server
Author: oreokebu-dev
License: MIT
License-File: LICENSE
Classifier: License :: OSI Approved :: MIT License
Classifier: Operating System :: OS Independent
Classifier: Programming Language :: Python
Classifier: Programming Language :: Python :: 3
Classifier: Programming Language :: Python :: 3.10
Classifier: Programming Language :: Python :: 3.11
Classifier: Programming Language :: Python :: 3.12
Classifier: Programming Language :: Python :: 3.13
Requires-Python: >=3.10
Requires-Dist: boto3>=1.39.4
Requires-Dist: loguru>=0.7.3
Requires-Dist: mcp[cli]>=1.11.0
Requires-Dist: pydantic>=2.10.5
Requires-Dist: typing-extensions>=4.13.2
